pyppm/__init__.py
pyppm/entropy.py
pyppm/help_functions.py
pyppm/hrpa.py
pyppm/loc.py
pyppm/rpa.py
pyppm_quantum-1.0.0.dist-info/LICENSE
pyppm_quantum-1.0.0.dist-info/METADATA
pyppm_quantum-1.0.0.dist-info/WHEEL
pyppm_quantum-1.0.0.dist-info/top_level.txt
pyppm_quantum-1.0.0.dist-info/RECORD
