Metadata-Version: 2.2
Name: pyppm_quantum
Version: 1.0.0
Summary: Python based Polarization Propagator Methods is a software based in PySCF that calculates 
Author-email: "Daniel F. E. Bajac" <danielbajac94@gmail.com>
License:                     GNU GENERAL PUBLIC LICENSE
Requires-Python: >=3.10
License-File: LICENSE
Requires-Dist: pyscf<2.8.0,>=2.4.0
Provides-Extra: dev
Requires-Dist: black; extra == "dev"
Requires-Dist: flake8; extra == "dev"
Requires-Dist: pytest; extra == "dev"
Requires-Dist: pytest-cov; extra == "dev"
Requires-Dist: tox; extra == "dev"
Requires-Dist: mypy; extra == "dev"
Requires-Dist: sphinx; extra == "dev"
Requires-Dist: sphinx_rtd_theme; extra == "dev"
Requires-Dist: pytest-mpl; extra == "dev"
